fuzzy_logic/__init__.py
fuzzy_logic/fuzzynumeric.py
fuzzy_logic/fuzzystring.py
fuzzy_logics-0.1.2.dist-info/LICENSE
fuzzy_logics-0.1.2.dist-info/METADATA
fuzzy_logics-0.1.2.dist-info/WHEEL
fuzzy_logics-0.1.2.dist-info/top_level.txt
fuzzy_logics-0.1.2.dist-info/RECORD
