Metadata-Version: 2.1
Name: fuzzy-logics
Version: 0.1.2
Summary: The library provides functions for fuzzy string matching, fuzzy round-off for floats and a fuzzy function of dividing a integer into a integer distribution according to given percentage.
Home-page: https://github.com/shubhankar-mohan/fuzzy_logic
Author: Shubhankar Mohan
Author-email: mohanshubhankar@gmail.com
License: UNKNOWN
Platform: UNKNOWN
Classifier: Programming Language :: Python :: 3
Classifier: License :: OSI Approved :: MIT License
Classifier: Operating System :: OS Independent
Requires-Python: >=3.5
Requires-Dist: numpy
